cryptsp/__init__.py
cryptsp-0.0.2.dist-info/METADATA
cryptsp-0.0.2.dist-info/WHEEL
cryptsp-0.0.2.dist-info/licenses/LICENSE.md
cryptsp-0.0.2.dist-info/RECORD
