Metadata-Version: 2.4
Name: cryptsp
Version: 0.0.2
Summary: A Python library offering a comprehensive collection of predefined encryption and decryption algorithms for secure and efficient cryptography.
Project-URL: Homepage, https://github.com/Vatsaboii/cryptsp
Project-URL: Issues, https://github.com/Vatsaboii/cryptsp
Author-email: Srivatsa Palepu <vatsaboii36@gmail.com>
License-File: LICENSE.md
Classifier: License :: OSI Approved :: GNU General Public License v3 (GPLv3)
Classifier: Operating System :: OS Independent
Classifier: Programming Language :: Python :: 3
Requires-Python: >=3.0
Requires-Dist: argon2-cffi>=23.1.0
Requires-Dist: bcrypt>=4.0.1
Requires-Dist: pycryptodome>=3.19.0
Requires-Dist: pyjwt>=2.10.1
Requires-Dist: python-jwt>=4.0.0
